pyomd/__init__.py
pyomd/config/__init__.py
pyomd/config/config.py
pyomd/config/default.yaml
pyomd/exceptions.py
pyomd/metadata.py
pyomd/misc.py
pyomd/note.py
py_obsidianmd-0.1.7.dist-info/LICENSE.txt
py_obsidianmd-0.1.7.dist-info/WHEEL
py_obsidianmd-0.1.7.dist-info/METADATA
py_obsidianmd-0.1.7.dist-info/RECORD
