Metadata-Version: 2.1
Name: py-obsidianmd
Version: 0.1.7
Summary: python library for ObsidianMD
Home-page: https://github.com/selimrbd/py-obsidianmd
License: MIT
Author: Selim Raboudi
Author-email: selim.raboudi@gmail.com
Requires-Python: >=3.10,<4.0
Classifier: License :: OSI Approved :: MIT License
Classifier: Programming Language :: Python :: 3
Classifier: Programming Language :: Python :: 3.10
Requires-Dist: python-frontmatter (>=1.0.0,<2.0.0)
Project-URL: Repository, https://github.com/selimrbd/py-obsidianmd
